phytools/__init__.py
phytools/constants.py
phytools/functions.py
phytools/misc.py
phytools/optics.py
phytools/signalproc.py
phytools-0.4.0.dist-info/AUTHORS
phytools-0.4.0.dist-info/LICENSE
phytools-0.4.0.dist-info/METADATA
phytools-0.4.0.dist-info/WHEEL
phytools-0.4.0.dist-info/pbr.json
phytools-0.4.0.dist-info/top_level.txt
phytools-0.4.0.dist-info/RECORD
