Metadata-Version: 2.1
Name: phytools
Version: 0.4.0
Summary: Useful tools for physicists.
Home-page: https://github.com/kricki/phytools
Author: kricki
License: UNKNOWN
Platform: UNKNOWN
Classifier: Development Status :: 4 - Beta
Classifier: Intended Audience :: Science/Research
Classifier: Intended Audience :: Developers
Classifier: Programming Language :: Python :: 3.6
Classifier: Topic :: Scientific/Engineering
Requires-Dist: scipy
Requires-Dist: numpy
